js_lib_htmx/__init__.py
js_lib_htmx/apps.py
js_lib_htmx/static/htmx/htmx.amd.js
js_lib_htmx/static/htmx/htmx.cjs.js
js_lib_htmx/static/htmx/htmx.esm.d.ts
js_lib_htmx/static/htmx/htmx.esm.js
js_lib_htmx/static/htmx/htmx.js
js_lib_htmx/static/htmx/htmx.min.js
js_lib_htmx/static/htmx/htmx.min.js.gz
js_lib_htmx/static/htmx/ext/README.md
js_lib_htmx/static/htmx/ext/_WARNING_DEPRECATED_FILES_.txt
js_lib_htmx/static/htmx/ext/ajax-header.js
js_lib_htmx/static/htmx/ext/alpine-morph.js
js_lib_htmx/static/htmx/ext/class-tools.js
js_lib_htmx/static/htmx/ext/client-side-templates.js
js_lib_htmx/static/htmx/ext/debug.js
js_lib_htmx/static/htmx/ext/disable-element.js
js_lib_htmx/static/htmx/ext/event-header.js
js_lib_htmx/static/htmx/ext/head-support.js
js_lib_htmx/static/htmx/ext/include-vals.js
js_lib_htmx/static/htmx/ext/json-enc.js
js_lib_htmx/static/htmx/ext/loading-states.js
js_lib_htmx/static/htmx/ext/method-override.js
js_lib_htmx/static/htmx/ext/morphdom-swap.js
js_lib_htmx/static/htmx/ext/multi-swap.js
js_lib_htmx/static/htmx/ext/path-deps.js
js_lib_htmx/static/htmx/ext/path-params.js
js_lib_htmx/static/htmx/ext/preload.js
js_lib_htmx/static/htmx/ext/rails-method.js
js_lib_htmx/static/htmx/ext/remove-me.js
js_lib_htmx/static/htmx/ext/response-targets.js
js_lib_htmx/static/htmx/ext/restored.js
js_lib_htmx/static/htmx/ext/sse.js
js_lib_htmx/static/htmx/ext/ws.js
django_js_lib_htmx-2.0.3.1.dist-info/LICENSE
django_js_lib_htmx-2.0.3.1.dist-info/WHEEL
django_js_lib_htmx-2.0.3.1.dist-info/METADATA
django_js_lib_htmx-2.0.3.1.dist-info/RECORD
