Metadata-Version: 2.1
Name: django-js-lib-htmx
Version: 2.0.3.1
Summary: HTMX Repackaged for Django
Classifier: License :: OSI Approved :: Zero-Clause BSD (0BSD)
